setup.py
cloudify_diamond_plugin.egg-info/PKG-INFO
cloudify_diamond_plugin.egg-info/SOURCES.txt
cloudify_diamond_plugin.egg-info/dependency_links.txt
cloudify_diamond_plugin.egg-info/requires.txt
cloudify_diamond_plugin.egg-info/top_level.txt
cloudify_handler/__init__.py
cloudify_handler/cloudify.py
cloudify_handler/format.py
diamond_agent/__init__.py
diamond_agent/tasks.py
diamond_agent/resources/diamond