Metadata-Version: 1.0
Name: cloudify-diamond-plugin
Version: 1.3.8
Summary: Cloudify Diamond monitoring plugin
Home-page: UNKNOWN
Author: Cloudify
Author-email: cosmo-admin@gigaspaces.com
License: LICENSE
Platform: UNKNOWN
